axiomos/__init__.py
axiomos/demo.py
axiomos/smoke.py
axiomos/verify.py
axiomos/backends/opencl_backend.py
axiomos/cli/__init__.py
axiomos/cli/axir_doctor.py
axiomos/cli/devices.py
axiomos/cli/export_torch.py
axiomos/cli/quick_demo.py
axiomos-0.1.18.dist-info/licenses/LICENSE
axiomos-0.1.18.dist-info/METADATA
axiomos-0.1.18.dist-info/WHEEL
axiomos-0.1.18.dist-info/entry_points.txt
axiomos-0.1.18.dist-info/top_level.txt
axiomos-0.1.18.dist-info/RECORD
