Metadata-Version: 2.4
Name: axiomos
Version: 0.1.18
Summary: A lightweight AXIR playground to run numerical kernels across CPU and OpenCL
Author: Axiomos
License: MIT
Project-URL: Homepage, https://github.com/Aidenkuro10/axiomos-vitrine
Project-URL: Documentation, https://github.com/Aidenkuro10/axiomos-vitrine#readme
Project-URL: Repository, https://github.com/Aidenkuro10/axiomos-vitrine
Keywords: opencl,kernels,gemm,axir,numpy,runtime,AI
Classifier: Development Status :: 3 - Alpha
Classifier: Programming Language :: Python :: 3
Classifier: License :: OSI Approved :: MIT License
Classifier: Operating System :: OS Independent
Requires-Python: >=3.10
License-File: LICENSE
Requires-Dist: numpy>=1.23
Requires-Dist: jsonschema>=4.21
Requires-Dist: tqdm>=4.0
Provides-Extra: opencl
Requires-Dist: pyopencl>=2022.3; extra == "opencl"
Provides-Extra: torch
Requires-Dist: torch; extra == "torch"
Dynamic: license-file
